pdfmerge/__init__.py
pdfmerge/main.py
pdfmerge_cli-0.2.0.dist-info/WHEEL
pdfmerge_cli-0.2.0.dist-info/LICENSE
pdfmerge_cli-0.2.0.dist-info/METADATA
pdfmerge_cli-0.2.0.dist-info/entry_points.txt
pdfmerge_cli-0.2.0.dist-info/RECORD
